resemblyzer/__init__.py
resemblyzer/audio.py
resemblyzer/hparams.py
resemblyzer/pretrained.pt
resemblyzer/voice_encoder.py
Resemblyzer-0.1.3.dist-info/LICENSE
Resemblyzer-0.1.3.dist-info/METADATA
Resemblyzer-0.1.3.dist-info/WHEEL
Resemblyzer-0.1.3.dist-info/top_level.txt
Resemblyzer-0.1.3.dist-info/RECORD
