Metadata-Version: 2.1
Name: Resemblyzer
Version: 0.1.3
Summary: Analyze and compare voices with deep learning
Home-page: https://github.com/resemble-ai/Resemblyzer
Author: Corentin Jemine
Author-email: corentin@resemble.ai
Classifier: Programming Language :: Python :: 3
Classifier: License :: OSI Approved :: Apache Software License
Classifier: Operating System :: OS Independent
Requires-Python: >=3.5
License-File: LICENSE
Requires-Dist: librosa (>=0.9.1)
Requires-Dist: numpy (>=1.10.1)
Requires-Dist: webrtcvad (>=2.0.10)
Requires-Dist: torch (>=1.0.1)
Requires-Dist: scipy (>=1.2.1)
Requires-Dist: typing
